catplot/__init__.py
catplot/canvas.py
catplot/chem_parser.py
catplot/descriptors.py
catplot/interpolate.py
catplot/ep_components/__init__.py
catplot/ep_components/descriptors.py
catplot/ep_components/ep_canvas.py
catplot/ep_components/ep_chain.py
catplot/ep_components/ep_lines.py
catplot/grid_components/__init__.py
catplot/grid_components/edges.py
catplot/grid_components/grid_canvas.py
catplot/grid_components/nodes.py
catplot/grid_components/planes.py
catplot/grid_components/supercell.py
catplot-1.3.3.dist-info/DESCRIPTION.rst
catplot-1.3.3.dist-info/METADATA
catplot-1.3.3.dist-info/RECORD
catplot-1.3.3.dist-info/WHEEL
catplot-1.3.3.dist-info/metadata.json
catplot-1.3.3.dist-info/top_level.txt
