Metadata-Version: 2.0
Name: catplot
Version: 1.3.3
Summary: A Python Library for Energy Profile and 2D/3D Lattice Grid Plotting
Home-page: https://github.com/PytLab/catplot
Author: Shao-Zheng-Jiang
Author-email: shaozhengjiang@gmail.com
License: LICENSE
Download-URL: https://github.com/PytLab/catplot/releases
Platform: linux
Platform: windows
Platform: macos
Requires-Dist: matplotlib (>=2.0.0)
Requires-Dist: numpy
Requires-Dist: scipy
